CHANGELOG.txt
LICENSE.txt
MANIFEST.in
README.txt
requirements.txt
setup.py
fossmeetups/__init__.py
fossmeetups.egg-info/PKG-INFO
fossmeetups.egg-info/SOURCES.txt
fossmeetups.egg-info/dependency_links.txt
fossmeetups.egg-info/requires.txt
fossmeetups.egg-info/top_level.txt
test/test.py
venv/Lib/site-packages/_distutils_hack/__init__.py
venv/Lib/site-packages/_distutils_hack/override.py
venv/Lib/site-packages/backports/__init__.py
venv/Lib/site-packages/backports.tarfile-1.2.0.dist-info/top_level.txt
venv/Lib/site-packages/backports/tarfile/__init__.py
venv/Lib/site-packages/backports/tarfile/__main__.py
venv/Lib/site-packages/backports/tarfile/compat/__init__.py
venv/Lib/site-packages/backports/tarfile/compat/py38.py
venv/Lib/site-packages/certifi/__init__.py
venv/Lib/site-packages/certifi/__main__.py
venv/Lib/site-packages/certifi/core.py
venv/Lib/site-packages/certifi-2024.6.2.dist-info/top_level.txt
venv/Lib/site-packages/charset_normalizer/__init__.py
venv/Lib/site-packages/charset_normalizer/__main__.py
venv/Lib/site-packages/charset_normalizer/api.py
venv/Lib/site-packages/charset_normalizer/cd.py
venv/Lib/site-packages/charset_normalizer/constant.py
venv/Lib/site-packages/charset_normalizer/legacy.py
venv/Lib/site-packages/charset_normalizer/md.py
venv/Lib/site-packages/charset_normalizer/models.py
venv/Lib/site-packages/charset_normalizer/utils.py
venv/Lib/site-packages/charset_normalizer/version.py
venv/Lib/site-packages/charset_normalizer-3.3.2.dist-info/entry_points.txt
venv/Lib/site-packages/charset_normalizer-3.3.2.dist-info/top_level.txt
venv/Lib/site-packages/charset_normalizer/cli/__init__.py
venv/Lib/site-packages/charset_normalizer/cli/__main__.py
venv/Lib/site-packages/docutils/__init__.py
venv/Lib/site-packages/docutils/__main__.py
venv/Lib/site-packages/docutils/core.py
venv/Lib/site-packages/docutils/examples.py
venv/Lib/site-packages/docutils/frontend.py
venv/Lib/site-packages/docutils/io.py
venv/Lib/site-packages/docutils/nodes.py
venv/Lib/site-packages/docutils/statemachine.py
venv/Lib/site-packages/docutils-0.21.2.dist-info/COPYING.txt
venv/Lib/site-packages/docutils-0.21.2.dist-info/entry_points.txt
venv/Lib/site-packages/docutils/languages/__init__.py
venv/Lib/site-packages/docutils/languages/af.py
venv/Lib/site-packages/docutils/languages/ar.py
venv/Lib/site-packages/docutils/languages/ca.py
venv/Lib/site-packages/docutils/languages/cs.py
venv/Lib/site-packages/docutils/languages/da.py
venv/Lib/site-packages/docutils/languages/de.py
venv/Lib/site-packages/docutils/languages/en.py
venv/Lib/site-packages/fossmeetups-0.0.1-py3.10.egg-info/SOURCES.txt
venv/Lib/site-packages/fossmeetups-0.0.1-py3.10.egg-info/dependency_links.txt
venv/Lib/site-packages/fossmeetups-0.0.1-py3.10.egg-info/installed-files.txt
venv/Lib/site-packages/fossmeetups-0.0.1-py3.10.egg-info/requires.txt
venv/Lib/site-packages/fossmeetups-0.0.1-py3.10.egg-info/top_level.txt
venv/Lib/site-packages/importlib_metadata-7.1.0.dist-info/top_level.txt
venv/Lib/site-packages/jaraco.classes-3.4.0.dist-info/top_level.txt
venv/Lib/site-packages/jaraco.context-5.3.0.dist-info/top_level.txt
venv/Lib/site-packages/jaraco.functools-4.0.1.dist-info/top_level.txt
venv/Lib/site-packages/keyring-25.2.1.dist-info/entry_points.txt
venv/Lib/site-packages/keyring-25.2.1.dist-info/top_level.txt
venv/Lib/site-packages/markdown_it_py-3.0.0.dist-info/entry_points.txt
venv/Lib/site-packages/pip-21.2.3.dist-info/LICENSE.txt
venv/Lib/site-packages/pip-21.2.3.dist-info/entry_points.txt
venv/Lib/site-packages/pip-21.2.3.dist-info/top_level.txt
venv/Lib/site-packages/pkginfo-1.11.1.dist-info/LICENSE.txt
venv/Lib/site-packages/pkginfo-1.11.1.dist-info/entry_points.txt
venv/Lib/site-packages/pkginfo-1.11.1.dist-info/top_level.txt
venv/Lib/site-packages/pygments-2.18.0.dist-info/entry_points.txt
venv/Lib/site-packages/pywin32_ctypes-0.2.2.dist-info/LICENSE.txt
venv/Lib/site-packages/pywin32_ctypes-0.2.2.dist-info/top_level.txt
venv/Lib/site-packages/readme_renderer-43.0.dist-info/top_level.txt
venv/Lib/site-packages/requests-2.32.3.dist-info/top_level.txt
venv/Lib/site-packages/requests_toolbelt-1.0.0.dist-info/top_level.txt
venv/Lib/site-packages/rfc3986-2.0.0.dist-info/top_level.txt
venv/Lib/site-packages/setuptools-57.4.0.dist-info/entry_points.txt
venv/Lib/site-packages/setuptools-57.4.0.dist-info/top_level.txt
venv/Lib/site-packages/tk-0.1.0.dist-info/top_level.txt
venv/Lib/site-packages/twine-5.1.0.dist-info/entry_points.txt
venv/Lib/site-packages/twine-5.1.0.dist-info/top_level.txt
venv/Lib/site-packages/urllib3-2.2.1.dist-info/licenses/LICENSE.txt
venv/Lib/site-packages/zipp-3.19.2.dist-info/top_level.txt
